LICENSE
MANIFEST.in
README.rst
setup.cfg
setup.py
Xnt.egg-info/PKG-INFO
Xnt.egg-info/SOURCES.txt
Xnt.egg-info/dependency_links.txt
Xnt.egg-info/entry_points.txt
Xnt.egg-info/requires.txt
Xnt.egg-info/top_level.txt
xnt/__init__.py
xnt/status_codes.py
xnt/tasks.py
xnt/version.py
xnt/xenant.py
xnt/build/__init__.py
xnt/build/cc.py
xnt/build/make.py
xnt/build/tex.py
xnt/tests/__init__.py
xnt/tests/compilercollectiontests.py
xnt/tests/maketests.py
xnt/tests/taskcompressiontests.py
xnt/tests/taskcopytests.py
xnt/tests/taskmisctests.py
xnt/tests/taskmkdirtests.py
xnt/tests/taskmovetests.py
xnt/tests/taskremovetests.py
xnt/tests/textests.py
xnt/tests/xenantargparsertests.py
xnt/vcs/__init__.py
xnt/vcs/cvs.py
xnt/vcs/git.py
xnt/vcs/hg.py