Metadata-Version: 1.1
Name: Xnt
Version: 0.6.3
Summary: High-Level build script for doing more complex build tasks
Home-page: https://github.com/devnulltao/Xnt
Author: Kenny Ballou
Author-email: kennethmgballou@gmail.com
License: UNKNOWN
Platform: Linux
Platform: Windows
Classifier: Development Status :: 4 - Beta
Classifier: Environment :: Console
Classifier: Intended Audience :: Developers
Classifier: License :: OSI Approved :: GNU General Public License v3 (GPLv3)
Classifier: Natural Language :: English
Classifier: Operating System :: Microsoft :: Windows :: Windows 7
Classifier: Operating System :: POSIX :: Linux
Classifier: Programming Language :: Python :: 2.7
Classifier: Programming Language :: Python :: 3
Classifier: Topic :: Software Development
Classifier: Topic :: Software Development :: Build Tools
Classifier: Topic :: Utilities
